qtmodernredux/__init__.py
qtmodernredux/qtmodernredux.py
qtmodernredux/apl_style/__init__.py
qtmodernredux/apl_style/style.py
qtmodernredux/apl_style/widgetstyle/__init__.py
qtmodernredux/apl_style/widgetstyle/base.py
qtmodernredux/apl_style/widgetstyle/checkbox.py
qtmodernredux/apl_style/widgetstyle/combobox.py
qtmodernredux/apl_style/widgetstyle/constants.py
qtmodernredux/apl_style/widgetstyle/groupbox.py
qtmodernredux/apl_style/widgetstyle/headerview.py
qtmodernredux/apl_style/widgetstyle/lineedit.py
qtmodernredux/apl_style/widgetstyle/progressbar.py
qtmodernredux/apl_style/widgetstyle/pushbutton.py
qtmodernredux/apl_style/widgetstyle/radiobutton.py
qtmodernredux/apl_style/widgetstyle/scrollarea.py
qtmodernredux/apl_style/widgetstyle/scrollbar.py
qtmodernredux/apl_style/widgetstyle/slider.py
qtmodernredux/apl_style/widgetstyle/spinbox.py
qtmodernredux/apl_style/widgetstyle/splitter.py
qtmodernredux/apl_style/widgetstyle/tableview.py
qtmodernredux/apl_style/widgetstyle/tabwidget.py
qtmodernredux/apl_style/widgetstyle/tabwidget_titlebar.py
qtmodernredux/apl_style/widgetstyle/toolbar.py
qtmodernredux/apl_style/widgetstyle/treeview.py
qtmodernredux/apl_style/windowstyle/__init__.py
qtmodernredux/apl_style/windowstyle/buttons.py
qtmodernredux/apl_style/windowstyle/constants.py
qtmodernredux/apl_style/windowstyle/frame.py
qtmodernredux/resources/__init__.py
qtmodernredux/resources/qt_resources.py
qtmodernredux/windowstyle/__init__.py
qtmodernredux/windowstyle/modernwindow.py
qtmodernredux/windowstyle/tabfilter.py
qtmodernredux/windowstyle/windowframe.py
qtmodernredux/windowstyle/windowresizer.py
qtmodernredux/windowstyle/windowtitlelabel.py
QtModernRedux-0.9.12.dist-info/LICENSE
QtModernRedux-0.9.12.dist-info/METADATA
QtModernRedux-0.9.12.dist-info/WHEEL
QtModernRedux-0.9.12.dist-info/top_level.txt
QtModernRedux-0.9.12.dist-info/RECORD
