Metadata-Version: 2.1
Name: QtModernRedux
Version: 0.9.12
Summary: a modern UI style for Python 3.x / PySide2 applications
Home-page: https://github.com/robertkist/qtmodernredux
Author: Robert Kist
Author-email: kr@robertkist.com
License: UNKNOWN
Platform: UNKNOWN
Classifier: Programming Language :: Python :: 3
Classifier: License :: OSI Approved :: MIT License
Classifier: Operating System :: OS Independent
Classifier: Programming Language :: Python :: 3.9
Requires-Python: >=3.9.4
License-File: LICENSE
Requires-Dist: PySide2 (>=5.15.2)
